gbigsmiles/.gitignore
gbigsmiles/__init__.py
gbigsmiles/__main__.py
gbigsmiles/_version.py
gbigsmiles/atom.py
gbigsmiles/atom_graph.py
gbigsmiles/big_smiles.py
gbigsmiles/bond.py
gbigsmiles/chem_resource.py
gbigsmiles/core.py
gbigsmiles/distribution.py
gbigsmiles/exception.py
gbigsmiles/generating_graph.py
gbigsmiles/nx_rdkit_mol.py
gbigsmiles/parser.py
gbigsmiles/smiles.py
gbigsmiles/stochastic.py
gbigsmiles/transformer.py
gbigsmiles/util.py
gbigsmiles/data/ffbonded.itp
gbigsmiles/data/ffnonbonded.itp
gbigsmiles/data/g-bigsmiles.lark
gbigsmiles/data/opls.par
gbigsmiles-0.3.3.1.dist-info/licenses/LICENSE
gbigsmiles-0.3.3.1.dist-info/METADATA
gbigsmiles-0.3.3.1.dist-info/WHEEL
gbigsmiles-0.3.3.1.dist-info/top_level.txt
gbigsmiles-0.3.3.1.dist-info/RECORD
