Metadata-Version: 2.4
Name: gbigsmiles
Version: 0.3.3.1
Summary: Bigsmiles extension handling the generation of ensemble smiles strings.
Author-email: Ludwig Schneider <ludwigschneider@uchicago.edu>, Gervasio Zaldivar <g.zaldivar@nyu.edu>, Yuan Tian <yuan.tian@nyu.edu>
License: GPL-3.0
Requires-Python: >=3.10
License-File: LICENSE
Requires-Dist: scipy
Requires-Dist: numpy
Requires-Dist: networkx
Requires-Dist: matplotlib
Requires-Dist: pytest
Requires-Dist: rdkit
Requires-Dist: lark
Requires-Dist: typing_extensions
Dynamic: license-file
